{"version":1,"resource":"file:///home/rtviii/dev/riboxyz/ribctl/__init__.py","entries":[{"id":"lS8u.py","timestamp":1694983633075},{"id":"NRlQ.py","timestamp":1694983691202},{"id":"JbjA.py","timestamp":1694983734700},{"id":"TX9e.py","timestamp":1694984163161},{"id":"LsCf.py","timestamp":1694984181505},{"id":"bwxp.py","timestamp":1694985584549},{"id":"Fs0F.py","timestamp":1694985594770},{"id":"dUsY.py","timestamp":1694997499067},{"id":"o357.py","source":"Renaming _ASSETS_PATH to ASSETS_PATH","timestamp":1694997507530},{"id":"m7iv.py","timestamp":1694997637148},{"id":"N39L.py","timestamp":1694997696138},{"id":"5PMB.py","timestamp":1694997817016},{"id":"w3uo.py","timestamp":1694997836412},{"id":"xxzq.py","timestamp":1694997866649},{"id":"bGLW.py","timestamp":1694997929416},{"id":"HSrK.py","timestamp":1694997967463},{"id":"3zsI.py","timestamp":1694998004314},{"id":"yVwH.py","timestamp":1694998125288},{"id":"NLv3.py","timestamp":1695010726318},{"id":"SMHQ.py","timestamp":1695012952809},{"id":"JpYL.py","timestamp":1695012962976},{"id":"STVL.py","timestamp":1695013025923},{"id":"65gd.py","timestamp":1695013042126},{"id":"cesm.py","timestamp":1695069514265},{"id":"USdr.py","timestamp":1695073002198},{"id":"Bmt3.py","timestamp":1695073019062}]}