{"version":1,"resource":"file:///home/rtviii/dev/riboxyz/ribctl/ribosome_assets.py","entries":[{"id":"jB7T.py","timestamp":1694897392702},{"id":"kJ6x.py","timestamp":1694900768715},{"id":"IrgN.py","timestamp":1694900896893},{"id":"yFbP.py","timestamp":1694901202045},{"id":"CJGF.py","timestamp":1694902880737},{"id":"H8Zb.py","timestamp":1694902900860},{"id":"1nAi.py","source":"Renaming chains_and_modified_cif to cif_and_chains","timestamp":1694903040136},{"id":"yvrS.py","timestamp":1694903075877},{"id":"oVNM.py","timestamp":1694909039288},{"id":"vLjb.py","timestamp":1694909075619},{"id":"dpY4.py","timestamp":1694909205974},{"id":"FW9k.py","timestamp":1694909244341},{"id":"dFaL.py","timestamp":1694909256864},{"id":"nKpE.py","timestamp":1694909711029},{"id":"ImtW.py","timestamp":1694909774729},{"id":"jPbn.py","timestamp":1694909808616},{"id":"8geX.py","source":"Renaming cif_and_chains to cif_modified_and_chains","timestamp":1694909820720},{"id":"QL81.py","timestamp":1694909883444},{"id":"lCAO.py","timestamp":1694911427351},{"id":"eURR.py","timestamp":1694911511522},{"id":"Wh8i.py","source":"Workspace Edit","timestamp":1694911523112},{"id":"IhQI.py","timestamp":1694911532589},{"id":"EeSm.py","timestamp":1694911638363},{"id":"WTpX.py","timestamp":1694911650143},{"id":"s61q.py","timestamp":1694911679097},{"id":"9kxX.py","timestamp":1694911802488},{"id":"bGxo.py","timestamp":1694911828055},{"id":"S7hF.py","timestamp":1694911854862},{"id":"P4jS.py","timestamp":1694911925412},{"id":"SsyX.py","timestamp":1694911936109},{"id":"UXLu.py","timestamp":1694911963589},{"id":"8btU.py","timestamp":1694911996029},{"id":"oi5b.py","timestamp":1694985871142},{"id":"Hyqf.py","timestamp":1695012497459},{"id":"KLoc.py","source":"Workspace Edit","timestamp":1695012521559}]}